hzzzwl_agriculture_mcp_x/__init__.py
hzzzwl_agriculture_mcp_x/server.py
hzzzwl_agriculture_mcp_x-0.2.7.dist-info/METADATA
hzzzwl_agriculture_mcp_x-0.2.7.dist-info/WHEEL
hzzzwl_agriculture_mcp_x-0.2.7.dist-info/entry_points.txt
hzzzwl_agriculture_mcp_x-0.2.7.dist-info/RECORD
