Metadata-Version: 2.4
Name: hzzzwl-agriculture-mcp-x
Version: 0.2.7
Summary: Tools for providing agricultural information
Author-email: hzzzwl <1085501772@qq.com>
License-Expression: GPL-3.0
Classifier: Programming Language :: Python :: 3
Requires-Python: >=3.12
Requires-Dist: httpx>=0.28.1
Requires-Dist: mcp[cli]>=1.9.0
